chibi_gitlab/__init__.py
chibi_gitlab/chibi_gitlab.py
chibi_gitlab/cli.py
chibi_gitlab/config.py
chibi_gitlab/urls.py
chibi_gitlab-0.0.1.dist-info/AUTHORS.rst
chibi_gitlab-0.0.1.dist-info/LICENSE
chibi_gitlab-0.0.1.dist-info/METADATA
chibi_gitlab-0.0.1.dist-info/WHEEL
chibi_gitlab-0.0.1.dist-info/entry_points.txt
chibi_gitlab-0.0.1.dist-info/top_level.txt
chibi_gitlab-0.0.1.dist-info/RECORD
