Metadata-Version: 2.1
Name: chibi_gitlab
Version: 0.0.1
Summary: libreria para hacer llamadas al api de gitlab
Home-page: https://github.com/dem4ply/chibi_gitlab
Author: dem4ply
Author-email: dem4ply@gmail.com
License: WTFPL
Keywords: chibi_gitlab
Classifier: Development Status :: 2 - Pre-Alpha
Classifier: Intended Audience :: Developers
Classifier: License :: Public Domain
Classifier: Natural Language :: English
Classifier: Programming Language :: Python :: 3.7
Classifier: Programming Language :: Python :: 3.8
License-File: LICENSE
License-File: AUTHORS.rst
Requires-Dist: chibi >=0.14.0
Requires-Dist: chibi-requests >=1.0.0
